volttron/driver/interfaces/dnp3/__init__.py
volttron/driver/interfaces/dnp3/dnp3.py
volttron_lib_dnp3_driver-0.1.2rc1.dist-info/LICENSE
volttron_lib_dnp3_driver-0.1.2rc1.dist-info/METADATA
volttron_lib_dnp3_driver-0.1.2rc1.dist-info/WHEEL
volttron_lib_dnp3_driver-0.1.2rc1.dist-info/RECORD
