Metadata-Version: 2.1
Name: volttron-lib-dnp3-driver
Version: 0.1.2rc1
Summary: A minimal implementation of a driver for the VOLTTRON platform.
Home-page: https://github.com/eclipse-volttron/volttron-lib-dnp3-driver
License: Apache-2.0
Author: VOLTTRON Team
Author-email: volttron@pnnl.gov
Requires-Python: >=3.10,<4.0
Classifier: Intended Audience :: Developers
Classifier: Intended Audience :: Information Technology
Classifier: Intended Audience :: Other Audience
Classifier: Intended Audience :: Science/Research
Classifier: License :: OSI Approved :: Apache Software License
Classifier: Programming Language :: Python :: 3
Classifier: Programming Language :: Python :: 3.10
Classifier: Programming Language :: Python :: 3.11
Classifier: Programming Language :: Python :: 3 :: Only
Requires-Dist: dnp3-python (>=0.2.3b3,<0.3.0)
Requires-Dist: volttron-lib-base-driver (>=0.2.0rc0,<0.3.0)
Project-URL: Repository, https://github.com/eclipse-volttron/volttron-lib-dnp3-driver
